ngff_zarr/__about__.py
ngff_zarr/__init__.py
ngff_zarr/_array_split.py
ngff_zarr/_supported_versions.py
ngff_zarr/_zarr_kwargs.py
ngff_zarr/_zarr_open_array.py
ngff_zarr/_zarr_types.py
ngff_zarr/cli.py
ngff_zarr/cli_input_to_ngff_image.py
ngff_zarr/config.py
ngff_zarr/detect_cli_io_backend.py
ngff_zarr/from_ngff_zarr.py
ngff_zarr/hcs.py
ngff_zarr/itk_image_to_ngff_image.py
ngff_zarr/memory_usage.py
ngff_zarr/multiscales.py
ngff_zarr/ngff_image.py
ngff_zarr/ngff_image_to_itk_image.py
ngff_zarr/nibabel_image_to_ngff_image.py
ngff_zarr/parse_metadata.py
ngff_zarr/rfc4.py
ngff_zarr/rfc4_validation.py
ngff_zarr/rfc9_zip.py
ngff_zarr/rich_dask_progress.py
ngff_zarr/task_count.py
ngff_zarr/to_multiscales.py
ngff_zarr/to_ngff_image.py
ngff_zarr/to_ngff_zarr.py
ngff_zarr/validate.py
ngff_zarr/zarr_metadata.py
ngff_zarr/methods/__init__.py
ngff_zarr/methods/_dask_image.py
ngff_zarr/methods/_itk.py
ngff_zarr/methods/_itkwasm.py
ngff_zarr/methods/_metadata.py
ngff_zarr/methods/_support.py
ngff_zarr/spec/0.1/copyright.include
ngff_zarr/spec/0.1/schemas/image.schema
ngff_zarr/spec/0.1/schemas/plate.schema
ngff_zarr/spec/0.1/schemas/strict_image.schema
ngff_zarr/spec/0.1/schemas/well.schema
ngff_zarr/spec/0.2/copyright.include
ngff_zarr/spec/0.2/schemas/image.schema
ngff_zarr/spec/0.2/schemas/plate.schema
ngff_zarr/spec/0.2/schemas/well.schema
ngff_zarr/spec/0.3/copyright.include
ngff_zarr/spec/0.3/schemas/image.schema
ngff_zarr/spec/0.3/schemas/plate.schema
ngff_zarr/spec/0.3/schemas/strict_image.schema
ngff_zarr/spec/0.3/schemas/well.schema
ngff_zarr/spec/0.3/schemas/jsonld/context.json
ngff_zarr/spec/0.3/schemas/jsonld/frame.json
ngff_zarr/spec/0.3/schemas/jsonld/shacl.ttl
ngff_zarr/spec/0.3/schemas/salad_schema/image.yml
ngff_zarr/spec/0.4/copyright.include
ngff_zarr/spec/0.4/schemas/bf2raw.schema
ngff_zarr/spec/0.4/schemas/image.schema
ngff_zarr/spec/0.4/schemas/label.schema
ngff_zarr/spec/0.4/schemas/ome.schema
ngff_zarr/spec/0.4/schemas/plate.schema
ngff_zarr-0.21.0.dist-info/METADATA
ngff_zarr-0.21.0.dist-info/WHEEL
ngff_zarr-0.21.0.dist-info/entry_points.txt
ngff_zarr-0.21.0.dist-info/RECORD
